vnet/__init__.py
vnet/config.py
vnetconfig-0.1.25.dist-info/LICENSE
vnetconfig-0.1.25.dist-info/METADATA
vnetconfig-0.1.25.dist-info/WHEEL
vnetconfig-0.1.25.dist-info/top_level.txt
vnetconfig-0.1.25.dist-info/RECORD
