Metadata-Version: 2.1
Name: vnetconfig
Version: 0.1.25
Summary: Package for extracting secret key-pairs
Home-page: https://github.com/pypa/sampleproject
Author: Gopinath Muthusamy
Author-email: gopinathmu@virtusa.com
Project-URL: Bug Tracker, https://github.com/pypa/sampleproject/issues
Classifier: Programming Language :: Python :: 3
Classifier: License :: OSI Approved :: MIT License
Classifier: Operating System :: OS Independent
Requires-Python: >=3.6
License-File: LICENSE
Requires-Dist: boto3
Requires-Dist: pymysql
